saluki/__init__.py
saluki/consume.py
saluki/listen.py
saluki/main.py
saluki/play.py
saluki/sniff.py
saluki/utils.py
saluki-0.0.5.dist-info/licenses/LICENSE
saluki-0.0.5.dist-info/METADATA
saluki-0.0.5.dist-info/WHEEL
saluki-0.0.5.dist-info/entry_points.txt
saluki-0.0.5.dist-info/top_level.txt
saluki-0.0.5.dist-info/RECORD
