Metadata-Version: 2.4
Name: saluki
Version: 0.0.5
Project-URL: Homepage, https://github.com/ISISComputingGroup/saluki
Project-URL: Bug Reports, https://github.com/ISISComputingGroup/saluki/issues
Project-URL: Source, https://github.com/ISISComputingGroup/saluki
License-File: LICENSE
Requires-Dist: ess-streaming-data-types
Requires-Dist: confluent-kafka>=2.12.1
Requires-Dist: python-dateutil
Requires-Dist: tzdata
Provides-Extra: dev
Requires-Dist: pyright; extra == "dev"
Requires-Dist: ruff; extra == "dev"
Requires-Dist: pytest; extra == "dev"
Requires-Dist: pytest-cov; extra == "dev"
Dynamic: license-file
